PicSimSearch/__init__.py
PicSimSearch/color.py
PicSimSearch/dataset.py
PicSimSearch/dependencies.py
PicSimSearch/engine.py
PicSimSearch/feature.py
PicSimSearch/prepare.py
PicSimSearch/similarity.py
PicSimSearch/utils.py
PicSimSearch/variables.py
PicSimSearch/Io/__init__.py
PicSimSearch/Io/read.py
PicSimSearch/Io/show.py
PicSimSearch/Io/upload.py
PicSimSearch-0.1.2.dist-info/LICENSE
PicSimSearch-0.1.2.dist-info/METADATA
PicSimSearch-0.1.2.dist-info/WHEEL
PicSimSearch-0.1.2.dist-info/top_level.txt
PicSimSearch-0.1.2.dist-info/RECORD
