Metadata-Version: 2.1
Name: PicSimSearch
Version: 0.1.2
Summary: Python package for image search based on keypoint-based feature extraction and matching 
Home-page: https://github.com/snmahsa/PicSimSearch
Author: Mahsa Sanaei
Author-email: mahsasanaei.n@gmail.com
License: MIT
Keywords: python3,clasification,find picture
License-File: LICENSE
Requires-Dist: aiofiles (==23.2.1)
Requires-Dist: aiohttp (==3.8.5)
Requires-Dist: aiosignal (==1.3.1)
Requires-Dist: altair (==5.0.1)
Requires-Dist: annotated-types (==0.5.0)
Requires-Dist: anyio (==3.7.1)
Requires-Dist: asttokens (==2.2.1)
Requires-Dist: async-timeout (==4.0.3)
Requires-Dist: attrs (==23.1.0)
Requires-Dist: backcall (==0.2.0)
Requires-Dist: certifi (==2023.7.22)
Requires-Dist: charset-normalizer (==3.2.0)
Requires-Dist: click (==8.1.7)
Requires-Dist: comm (==0.1.3)
Requires-Dist: contourpy (==1.1.0)
Requires-Dist: cycler (==0.11.0)
Requires-Dist: debugpy (==1.6.7)
Requires-Dist: decorator (==5.1.1)
Requires-Dist: deprecation (==2.1.0)
Requires-Dist: exceptiongroup (==1.1.3)
Requires-Dist: executing (==1.2.0)
Requires-Dist: fastapi (==0.101.1)
Requires-Dist: ffmpy (==0.3.1)
Requires-Dist: filelock (==3.12.2)
Requires-Dist: fonttools (==4.42.1)
Requires-Dist: frozenlist (==1.4.0)
Requires-Dist: fsspec (==2023.6.0)
Requires-Dist: glob2 (==0.7)
Requires-Dist: gradio (==3.40.1)
Requires-Dist: gradio-client (==0.4.0)
Requires-Dist: h11 (==0.14.0)
Requires-Dist: httpcore (==0.17.3)
Requires-Dist: httpx (==0.24.1)
Requires-Dist: huggingface-hub (==0.16.4)
Requires-Dist: idna (==3.4)
Requires-Dist: ImageHash (==4.3.1)
Requires-Dist: imageio (==2.31.1)
Requires-Dist: img2pdf (==0.4.4)
Requires-Dist: importlib-resources (==6.0.1)
Requires-Dist: ipykernel (==6.23.3)
Requires-Dist: ipython (==8.14.0)
Requires-Dist: jedi (==0.18.2)
Requires-Dist: Jinja2 (==3.1.2)
Requires-Dist: jsonschema (==4.19.0)
Requires-Dist: jsonschema-specifications (==2023.7.1)
Requires-Dist: jupyter-client (==8.3.0)
Requires-Dist: jupyter-core (==5.3.1)
Requires-Dist: kiwisolver (==1.4.4)
Requires-Dist: lazy-loader (==0.3)
Requires-Dist: linkify-it-py (==2.0.2)
Requires-Dist: lxml (==4.9.3)
Requires-Dist: markdown-it-py (==2.2.0)
Requires-Dist: MarkupSafe (==2.1.3)
Requires-Dist: matplotlib (==3.7.2)
Requires-Dist: matplotlib-inline (==0.1.6)
Requires-Dist: mdit-py-plugins (==0.3.3)
Requires-Dist: mdurl (==0.1.2)
Requires-Dist: multidict (==6.0.4)
Requires-Dist: nest-asyncio (==1.5.6)
Requires-Dist: networkx (==3.1)
Requires-Dist: numpy (==1.25.2)
Requires-Dist: opencv-python (==4.8.0.76)
Requires-Dist: orjson (==3.9.5)
Requires-Dist: packaging (==23.1)
Requires-Dist: pandas (==2.0.3)
Requires-Dist: parso (==0.8.3)
Requires-Dist: pexpect (==4.8.0)
Requires-Dist: pickle-mixin (==1.0.2)
Requires-Dist: pickleshare (==0.7.5)
Requires-Dist: pikepdf (==8.1.1)
Requires-Dist: Pillow (==10.0.0)
Requires-Dist: platformdirs (==3.8.0)
Requires-Dist: prompt-toolkit (==3.0.38)
Requires-Dist: psutil (==5.9.5)
Requires-Dist: ptyprocess (==0.7.0)
Requires-Dist: pure-eval (==0.2.2)
Requires-Dist: pydantic (==2.2.1)
Requires-Dist: pydantic-core (==2.6.1)
Requires-Dist: pydub (==0.25.1)
Requires-Dist: Pygments (==2.15.1)
Requires-Dist: pyparsing (==3.0.9)
Requires-Dist: python-dateutil (==2.8.2)
Requires-Dist: python-multipart (==0.0.6)
Requires-Dist: pytz (==2023.3)
Requires-Dist: PyWavelets (==1.4.1)
Requires-Dist: PyYAML (==6.0.1)
Requires-Dist: pyzmq (==25.1.0)
Requires-Dist: referencing (==0.30.2)
Requires-Dist: requests (==2.31.0)
Requires-Dist: rpds-py (==0.9.2)
Requires-Dist: scikit-image (==0.21.0)
Requires-Dist: scipy (==1.9.3)
Requires-Dist: semantic-version (==2.10.0)
Requires-Dist: six (==1.16.0)
Requires-Dist: sniffio (==1.3.0)
Requires-Dist: stack-data (==0.6.2)
Requires-Dist: starlette (==0.27.0)
Requires-Dist: tifffile (==2023.8.12)
Requires-Dist: toolz (==0.12.0)
Requires-Dist: tornado (==6.3.2)
Requires-Dist: tqdm (==4.66.1)
Requires-Dist: traitlets (==5.9.0)
Requires-Dist: typing-extensions (==4.7.1)
Requires-Dist: tzdata (==2023.3)
Requires-Dist: uc-micro-py (==1.0.2)
Requires-Dist: urllib3 (==2.0.4)
Requires-Dist: uvicorn (==0.23.2)
Requires-Dist: wcwidth (==0.2.6)
Requires-Dist: websockets (==11.0.3)
Requires-Dist: yarl (==1.9.2)
